curated_tokenizers/_spp.cpython-39-darwin.so
curated_tokenizers/merges.cc
curated_tokenizers/_bbpe.cpython-39-darwin.so
curated_tokenizers/config.h
curated_tokenizers/_wordpiece.pxd
curated_tokenizers/_bbpe.pyx
curated_tokenizers/__init__.py
curated_tokenizers/_spp.pyx
curated_tokenizers/types.py
curated_tokenizers/merges.hh
curated_tokenizers/wordpiece.cc
curated_tokenizers/_spp.pxd
curated_tokenizers/_wordpiece.cpython-39-darwin.so
curated_tokenizers/_util.py
curated_tokenizers/py.typed
curated_tokenizers/_bbpe.pxd
curated_tokenizers/_wordpiece.pyx
curated_tokenizers/wordpiece.hh
curated_tokenizers/util.hh
curated_tokenizers/tests/conftest.py
curated_tokenizers/tests/troonrede.txt
curated_tokenizers/tests/toy-word-pieces.txt
curated_tokenizers/tests/test_bbpe_processor.py
curated_tokenizers/tests/compat.py
curated_tokenizers/tests/test_word_piece_processor.py
curated_tokenizers/tests/__init__.py
curated_tokenizers/tests/test_sp.py
curated_tokenizers/tests/robbert-merges-1000.txt
curated_tokenizers/tests/toy.model
curated_tokenizers/tests/incorrect-merges.txt
curated_tokenizers/tests/robbert-vocab-1000.json
curated_tokenizers-2.0.0.dist-info/zip-safe
curated_tokenizers-2.0.0.dist-info/RECORD
curated_tokenizers-2.0.0.dist-info/LICENSE
curated_tokenizers-2.0.0.dist-info/WHEEL
curated_tokenizers-2.0.0.dist-info/top_level.txt
curated_tokenizers-2.0.0.dist-info/METADATA
